PySAM_DAOTk_stubs/AdjustmentFactors.pyi
PySAM_DAOTk_stubs/Annualoutput.pyi
PySAM_DAOTk_stubs/Battery.pyi
PySAM_DAOTk_stubs/BatteryStateful.pyi
PySAM_DAOTk_stubs/Battwatts.pyi
PySAM_DAOTk_stubs/Belpe.pyi
PySAM_DAOTk_stubs/Biomass.pyi
PySAM_DAOTk_stubs/Cashloan.pyi
PySAM_DAOTk_stubs/CbConstructionFinancing.pyi
PySAM_DAOTk_stubs/CbEmpiricalHceHeatLoss.pyi
PySAM_DAOTk_stubs/CbMsptSystemCosts.pyi
PySAM_DAOTk_stubs/DsgFluxPreprocess.pyi
PySAM_DAOTk_stubs/Equpartflip.pyi
PySAM_DAOTk_stubs/Fuelcell.pyi
PySAM_DAOTk_stubs/GenericSystem.pyi
PySAM_DAOTk_stubs/Geothermal.pyi
PySAM_DAOTk_stubs/GeothermalCosts.pyi
PySAM_DAOTk_stubs/Grid.pyi
PySAM_DAOTk_stubs/Hcpv.pyi
PySAM_DAOTk_stubs/HostDeveloper.pyi
PySAM_DAOTk_stubs/Iec61853interp.pyi
PySAM_DAOTk_stubs/Iec61853par.pyi
PySAM_DAOTk_stubs/InvCecCg.pyi
PySAM_DAOTk_stubs/IphToLcoefcr.pyi
PySAM_DAOTk_stubs/Ippppa.pyi
PySAM_DAOTk_stubs/Irradproc.pyi
PySAM_DAOTk_stubs/IsccDesignPoint.pyi
PySAM_DAOTk_stubs/Layoutarea.pyi
PySAM_DAOTk_stubs/Lcoefcr.pyi
PySAM_DAOTk_stubs/Levpartflip.pyi
PySAM_DAOTk_stubs/LinearFresnelDsgIph.pyi
PySAM_DAOTk_stubs/Merchantplant.pyi
PySAM_DAOTk_stubs/MhkCosts.pyi
PySAM_DAOTk_stubs/MhkTidal.pyi
PySAM_DAOTk_stubs/MhkWave.pyi
PySAM_DAOTk_stubs/Poacalib.pyi
PySAM_DAOTk_stubs/Pv6parmod.pyi
PySAM_DAOTk_stubs/PvGetShadeLossMpp.pyi
PySAM_DAOTk_stubs/Pvsamv1.pyi
PySAM_DAOTk_stubs/Pvsandiainv.pyi
PySAM_DAOTk_stubs/Pvwattsv1.pyi
PySAM_DAOTk_stubs/Pvwattsv11ts.pyi
PySAM_DAOTk_stubs/Pvwattsv1Poa.pyi
PySAM_DAOTk_stubs/Pvwattsv5.pyi
PySAM_DAOTk_stubs/Pvwattsv51ts.pyi
PySAM_DAOTk_stubs/Pvwattsv7.pyi
PySAM_DAOTk_stubs/Saleleaseback.pyi
PySAM_DAOTk_stubs/Sco2AirCooler.pyi
PySAM_DAOTk_stubs/Sco2CspSystem.pyi
PySAM_DAOTk_stubs/Sco2CspUdPcTables.pyi
PySAM_DAOTk_stubs/Sco2DesignCycle.pyi
PySAM_DAOTk_stubs/Sco2DesignPoint.pyi
PySAM_DAOTk_stubs/Singlediode.pyi
PySAM_DAOTk_stubs/Singlediodeparams.pyi
PySAM_DAOTk_stubs/Singleowner.pyi
PySAM_DAOTk_stubs/SixParsolve.pyi
PySAM_DAOTk_stubs/Snowmodel.pyi
PySAM_DAOTk_stubs/Solarpilot.pyi
NREL_PySAM_DAO_Tk_stubs-1.3.3.dist-info/LICENSE
NREL_PySAM_DAO_Tk_stubs-1.3.3.dist-info/METADATA
NREL_PySAM_DAO_Tk_stubs-1.3.3.dist-info/WHEEL
NREL_PySAM_DAO_Tk_stubs-1.3.3.dist-info/top_level.txt
NREL_PySAM_DAO_Tk_stubs-1.3.3.dist-info/RECORD
