Metadata-Version: 2.1
Name: NREL-PySAM-DAO-Tk-stubs
Version: 1.3.3
Summary: National Renewable Energy Laboratory's System Advisor Model DAO-Tk Python Wrapper, stub files
Home-page: https://github.com/NREL/lore/tree/develop/pysam
Author: Matthew-Boyd
Author-email: matthew.boyd@nrel.gov
License: BSD 3-Clause
Platform: UNKNOWN
